onsort/__init__.py
onsort/analysis/sort_analyzer.py
onsort/continuous/__init__ .py
onsort/continuous/cont_prob.py
onsort/continuous/cont_prob_rational.py
onsort/continuous/cont_symbolic.py
onsort/continuous/cont_thresholds.py
onsort/continuous/my_sort.py
onsort/continuous/online_sort.py
onsort/discrete/discrete_prob.py
onsort/discrete/discrete_prob_symb.py
onsort-0.1.0.dist-info/METADATA
onsort-0.1.0.dist-info/WHEEL
onsort-0.1.0.dist-info/RECORD
