Metadata-Version: 2.1
Name: onsort
Version: 0.1.0
Summary: SOPA Algorithm, best possible probability sorting Algorithm
Author: Pablo Ruiz
Author-email: pablo.r.c@live.com
Requires-Python: >=3.11,<4.0
Classifier: Programming Language :: Python :: 3
Classifier: Programming Language :: Python :: 3.11
Classifier: Programming Language :: Python :: 3.12
Requires-Dist: matplotlib (>=3.7.0,<4.0.0)
Requires-Dist: numpy (>=1.26.4,<2.0.0)
Requires-Dist: scipy (>=1.11.3,<2.0.0)
Requires-Dist: sympy (>=1.12,<2.0)
